stdio_proxy/__init__.py
stdio_proxy/py.typed
stdio_proxy/py2.py
stdio_proxy/py3.py
stdio_proxy-0.1.3.dist-info/LICENSE
stdio_proxy-0.1.3.dist-info/METADATA
stdio_proxy-0.1.3.dist-info/WHEEL
stdio_proxy-0.1.3.dist-info/top_level.txt
stdio_proxy-0.1.3.dist-info/RECORD
