Metadata-Version: 2.1
Name: stdio-proxy
Version: 0.1.3
Summary: Thread safe stdio proxy
Home-page: https://github.com/bonprosoft/stdio_proxy
Author: Yuki Igarashi
Author-email: me@bonprosoft.com
License: MIT License
Platform: UNKNOWN
Classifier: Programming Language :: Python :: 2
Classifier: Programming Language :: Python :: 2.7
Classifier: Programming Language :: Python :: 3.5
Classifier: Programming Language :: Python :: 3.6
Classifier: Programming Language :: Python :: 3.7
Classifier: Programming Language :: Python :: 3.8
Classifier: Programming Language :: Python :: 3.9
Classifier: Programming Language :: Python
Classifier: License :: OSI Approved :: MIT License
Requires-Dist: futures ; python_version == "2.7"
Provides-Extra: develop
Requires-Dist: typing ; (python_version == "2.7") and extra == 'develop'
